openkv/__init__.py
openkv/openKV.py
openkv-0.1.0.dist-info/LICENSE
openkv-0.1.0.dist-info/METADATA
openkv-0.1.0.dist-info/WHEEL
openkv-0.1.0.dist-info/entry_points.txt
openkv-0.1.0.dist-info/RECORD
